README.md
setup.cfg
setup.py
liputils/__init__.py
liputils/liputils.py
liputils.egg-info/PKG-INFO
liputils.egg-info/SOURCES.txt
liputils.egg-info/dependency_links.txt
liputils.egg-info/requires.txt
liputils.egg-info/top_level.txt