Metadata-Version: 2.1
Name: liputils
Version: 0.16.2
Summary: A small Python package to manipulate complex lipids.
Home-page: https://github.com/Stemanz/liputils
Author: Stefano Manzini
Author-email: stefano.manzini@gmail.com
License: GPL-3.0
Download-URL: https://github.com/Stemanz/liputils/archive/master.zip
Keywords: lipids,lipids residues,lipidomics
Platform: UNKNOWN
